battleship/__init__.py
battleship/__main__.py
battleship/cli/__init__.py
battleship/cli/__main__.py
battleship/cli/account.py
battleship/cli/app.py
battleship/cli/console.py
battleship/cli/logging.py
battleship/cli/play.py
battleship/cli/settings.py
battleship/client/__init__.py
battleship/client/auth.py
battleship/client/client.py
battleship/client/credentials.py
battleship/client/subscriptions.py
battleship/client/websocket.py
battleship/engine/__init__.py
battleship/engine/ai.py
battleship/engine/api.py
battleship/engine/domain.py
battleship/engine/errors.py
battleship/engine/rosters.py
battleship/py.typed
battleship/server/__init__.py
battleship/server/app.py
battleship/server/auth.py
battleship/server/bus.py
battleship/server/config.py
battleship/server/context.py
battleship/server/di.py
battleship/server/game.py
battleship/server/handlers.py
battleship/server/metrics.py
battleship/server/repositories/__init__.py
battleship/server/repositories/clients.py
battleship/server/repositories/observable.py
battleship/server/repositories/sessions.py
battleship/server/repositories/statistics.py
battleship/server/repositories/subscriptions.py
battleship/server/routes.py
battleship/server/services.py
battleship/server/websocket.py
battleship/shared/__init__.py
battleship/shared/compat.py
battleship/shared/events.py
battleship/shared/models.py
battleship/tui/__init__.py
battleship/tui/app.py
battleship/tui/config.py
battleship/tui/di.py
battleship/tui/format.py
battleship/tui/i18n.py
battleship/tui/resources/create_game_help.md
battleship/tui/resources/lobby_help.md
battleship/tui/resources/multiplayer_help.md
battleship/tui/resources/settings_help.md
battleship/tui/resources/singleplayer_help.md
battleship/tui/resources/statistics_help.md
battleship/tui/resources.py
battleship/tui/screens/__init__.py
battleship/tui/screens/create_game.py
battleship/tui/screens/game.py
battleship/tui/screens/join_game.py
battleship/tui/screens/lobby.py
battleship/tui/screens/main_menu.py
battleship_tui-1.0.0.dist-info/LICENSE
battleship_tui-1.0.0.dist-info/METADATA
battleship_tui-1.0.0.dist-info/WHEEL
battleship_tui-1.0.0.dist-info/entry_points.txt
battleship_tui-1.0.0.dist-info/RECORD
