Metadata-Version: 2.1
Name: battleship-tui
Version: 1.0.0
Summary: Battleship TUI is an implementation of the popular paper-and-pen Battleship game for your terminal.
Home-page: https://github.com/Klavionik/battleship-tui
License: GPL-2.0-or-later
Keywords: battleship,game,tui
Author: Roman Vlasenko
Author-email: klavionik@gmail.com
Requires-Python: >=3.10,<3.13
Classifier: Development Status :: 3 - Alpha
Classifier: Environment :: Console
Classifier: Intended Audience :: Developers
Classifier: Intended Audience :: End Users/Desktop
Classifier: Intended Audience :: Other Audience
Classifier: License :: OSI Approved :: GNU General Public License v2 or later (GPLv2+)
Classifier: Operating System :: MacOS
Classifier: Operating System :: Microsoft :: Windows :: Windows 10
Classifier: Operating System :: Microsoft :: Windows :: Windows 11
Classifier: Operating System :: POSIX :: Linux
Classifier: Programming Language :: Python :: 3
Classifier: Programming Language :: Python :: 3.10
Classifier: Programming Language :: Python :: 3.11
Classifier: Topic :: Games/Entertainment :: Board Games
Classifier: Typing :: Typed
Provides-Extra: client
Provides-Extra: dev
Provides-Extra: server
Requires-Dist: aioprometheus (>=23.3.0,<24.0.0) ; extra == "server"
Requires-Dist: async-timeout (>=4.0.3,<5.0.0) ; (python_version < "3.11") and (extra == "client")
Requires-Dist: auth0-python (>=4.5.0,<5.0.0) ; extra == "server"
Requires-Dist: backports-strenum (>=1.2.8,<2.0.0) ; python_version < "3.11"
Requires-Dist: blacksheep (>=2.0.7,<3.0.0) ; extra == "server"
Requires-Dist: copykitten (>=1.1.1,<2.0.0) ; extra == "client"
Requires-Dist: email-validator (>=2.1.0.post1,<3.0.0)
Requires-Dist: httpx (>=0.27.0,<0.28.0)
Requires-Dist: inject (>=5.1.0,<6.0.0) ; extra == "client"
Requires-Dist: loguru (>=0.7.0,<0.8.0)
Requires-Dist: pydantic (>=2.6.0,<3.0.0)
Requires-Dist: pydantic-settings (>=2.2.0,<3.0.0)
Requires-Dist: pyee (>=11.0.0,<12.0.0)
Requires-Dist: pyjwt[crypto] (>=2.8.0,<3.0.0) ; extra == "server"
Requires-Dist: pymitter (>=0.5.1,<0.6.0)
Requires-Dist: redis (>=5.0.1,<6.0.0) ; extra == "server"
Requires-Dist: sentry-offline-transport (>=1.0.0,<2.0.0) ; extra == "client"
Requires-Dist: sentry-sdk (>=2.2.1,<3.0.0)
Requires-Dist: tenacity (>=8.2.3,<9.0.0) ; extra == "client"
Requires-Dist: textual (>=0.52.0,<0.53.0) ; extra == "client"
Requires-Dist: textual-dev (>=1.5.0,<2.0.0) ; extra == "dev"
Requires-Dist: typer (>=0.9.0,<0.10.0) ; extra == "client"
Requires-Dist: uvicorn (>=0.27.0,<0.28.0) ; extra == "server"
Requires-Dist: uvloop (>=0.19.0,<0.20.0) ; extra == "server"
Requires-Dist: websockets (>=12.0.0,<13.0.0)
Requires-Dist: xdg-base-dirs (>=6.0.1,<7.0.0)
